zestreleaser/towncrier/__init__.py
zestreleaser_towncrier-2.0.0.dist-info/licenses/LICENSE.GPL
zestreleaser_towncrier-2.0.0.dist-info/licenses/LICENSE.rst
zestreleaser_towncrier-2.0.0.dist-info/METADATA
zestreleaser_towncrier-2.0.0.dist-info/WHEEL
zestreleaser_towncrier-2.0.0.dist-info/entry_points.txt
zestreleaser_towncrier-2.0.0.dist-info/top_level.txt
zestreleaser_towncrier-2.0.0.dist-info/RECORD
